Metadata-Version: 1.1
Name: digital-comms
Version: 0.1.5
Summary: The ITRC MISTRAL Digital Communications Model
Home-page: http://www.itrc.org.uk
Author: Dr. Edward J. Oughton
Author-email: e.oughton@jbs.cam.ac.uk
License: mit
Platform: UNKNOWN
Classifier: Development Status :: 4 - Beta
Classifier: Programming Language :: Python
Classifier: Intended Audience :: Science/Research
Classifier: License :: OSI Approved :: MIT License
Classifier: Natural Language :: English
Classifier: Topic :: Scientific/Engineering
